pi/__init__.py
pi/_internal/__init__.py
pi/_internal/ai_conn.py
pi/_internal/app.py
pi/_internal/bus.py
pi/_internal/dataclass_extras.py
pi/_internal/namespace.py
pi/_internal/rpc.py
pi/_internal/screen.py
pi/_internal/typecache.py
pi/_internal/typing_eval.py
pi/_internal/typing_inspect.py
pi/_internal/agents/__init__.py
pi/_internal/agents/common.py
pi/_internal/agents/core.py
pi/_internal/agents/deps.py
pi/_internal/agents/history.py
pi/_internal/agents/loop.py
pi/_internal/agents/storage.py
pi/_internal/agents/ui_adapter.py
pi/_internal/agents/prompts/PI_PROMPT.md
pi/_internal/agents/tools/context.py
pi/_internal/agents/tools/edit.py
pi/_internal/agents/tools/exec_pi_captive.py
pi/_internal/agents/tools/exec_raw.py
pi/_internal/agents/tools/shell.py
pi/_internal/build/__init__.py
pi/_internal/build/rpc_schema.py
pi/_internal/protocols/__init__.py
pi/_internal/protocols/project.py
pi/_internal/protocols/router.py
pi/_internal/protocols/shell.py
pi/_internal/ui/models/chattables.py
pi/_internal/ui/models/panelables.py
pi/_internal/ui/models/pickables.py
pi/_internal/ui/widgets/chat.py
pi/_internal/ui/widgets/control.py
pi/_internal/ui/widgets/graphics.py
pi/_internal/ui/widgets/layout.py
pi/_internal/ui/widgets/panel.py
pi/_internal/ui/widgets/picker.py
pi-1.0.0.dev2.data/scripts/pi
pi-1.0.0.dev2.dist-info/METADATA
pi-1.0.0.dev2.dist-info/WHEEL
pi-1.0.0.dev2.dist-info/RECORD
