Metadata-Version: 2.4
Name: pi
Version: 1.0.0.dev2
Classifier: Development Status :: 3 - Alpha
Classifier: Intended Audience :: Developers
Classifier: Programming Language :: Python :: 3
Classifier: Programming Language :: Python :: 3.13
Requires-Dist: pydantic-ai-slim[openai,anthropic,google,mistral]~=1.16.0
Requires-Dist: pi-tokenize~=0.0.1
Requires-Dist: textual==6.5.0
Requires-Dist: rapidfuzz~=3.14.3
Requires-Dist: pyperclip~=1.11.0
Requires-Dist: wcwidth~=0.2.14
Summary: Python Intelligence
Author-email: Yury Selivanov <yury@geldata.com>
Requires-Python: ==3.13.*
Project-URL: Repository, https://github.com/geldata/pi
